{
  "_class": "group",
  "booleanOperation": -1,
  "clippingMaskMode": 0,
  "do_objectID": "4778713F-F2A9-42F4-A5A2-8359A62F3647",
  "exportOptions": {
    "_class": "exportOptions",
    "do_objectID": "B3ECFAA7-3BE0-40B8-9E0A-5E389EA317A0",
    "exportFormats": [
    ],
    "includedLayerIds": [
    ],
    "layerOptions": 0,
    "shouldTrim": false
  },
  "frame": {
    "_class": "rect",
    "constrainProportions": false,
    "do_objectID": "DF18E25E-36DA-4F3E-B119-72A6E50FBF77",
    "height": 31,
    "width": 31,
    "x": 0.8994721921180826,
    "y": 81.18094181763854
  },
  "groupLayout": {
    "_class": "MSImmutableFreeformGroupLayout",
    "do_objectID": "2B9BF581-0570-4F29-A766-7DC2FD1C9746"
  },
  "hasClickThrough": false,
  "hasClippingMask": false,
  "isFixedToViewport": false,
  "isFlippedHorizontal": false,
  "isFlippedVertical": false,
  "isLocked": false,
  "isVisible": true,
  "layerListExpandedType": 0,
  "layers": [
    {
      "class": "shapeGroup",
      "id": "B2870B4D-D527-4FA4-A30B-382652AC1279"
    },
    {
      "class": "shapePath",
      "id": "66C8199D-73CB-401C-B9F2-864B3778078F"
    },
    {
      "class": "shapePath",
      "id": "DE6C2098-C7B9-4DE2-A68B-0E42632355F1"
    },
    {
      "class": "shapePath",
      "id": "F59E800D-0441-4AC2-BA9A-B97ABD1EFCAC"
    },
    {
      "class": "shapePath",
      "id": "6D22A584-59CD-4705-B2A0-42AB428B6CCA"
    },
    {
      "class": "shapePath",
      "id": "2B39FE28-05A2-43C8-85B9-B2E4A13706EF"
    },
    {
      "class": "shapePath",
      "id": "5FEFA2BE-307A-4073-95D0-28038CBA1BAC"
    },
    {
      "class": "shapePath",
      "id": "7BD298B1-5AD0-4E85-9ED8-20700854C268"
    },
    {
      "class": "shapePath",
      "id": "A3E2E699-42E4-4EDE-A858-0FEBC1D7F61F"
    },
    {
      "class": "shapePath",
      "id": "2DEC26D7-B8FB-4516-AD46-86A7AD2FE729"
    },
    {
      "class": "shapePath",
      "id": "81D80FF5-4D4D-404F-B1D2-18B00CBC2EEF"
    },
    {
      "class": "shapePath",
      "id": "48374FB8-A2F2-4390-BC4B-955BD60A0A35"
    },
    {
      "class": "shapePath",
      "id": "BC415B48-10DA-490A-B6F4-30CF4B2FA55A"
    }
  ],
  "name": "Group 2",
  "nameIsFixed": false,
  "resizingConstraint": 63,
  "resizingType": 0,
  "rotation": 0,
  "shouldBreakMaskChain": false,
  "style": {
    "_class": "style",
    "blur": {
      "_class": "blur",
      "center": "{0.5, 0.5}",
      "do_objectID": "5EA58AAA-7D4F-4B00-B05D-55159AFD8273",
      "isEnabled": false,
      "motionAngle": 0,
      "radius": 7,
      "saturation": 1,
      "type": 0
    },
    "do_objectID": "058B197B-2A49-47D2-8A8C-A48CB4071F4B",
    "endMarkerType": 0,
    "miterLimit": 10,
    "startMarkerType": 0,
    "windingRule": 1
  }
}