{
  "_class": "shapePath",
  "booleanOperation": -1,
  "clippingMaskMode": 0,
  "do_objectID": "4D2D5574-D775-4426-AD11-0157E91DFF9E",
  "edited": true,
  "exportOptions": {
    "_class": "exportOptions",
    "do_objectID": "67E32260-1483-4541-9BD0-D56F9606F7F0",
    "exportFormats": [
    ],
    "includedLayerIds": [
    ],
    "layerOptions": 0,
    "shouldTrim": false
  },
  "frame": {
    "_class": "rect",
    "constrainProportions": false,
    "do_objectID": "372AE001-DDC0-4178-B5B4-F4AC87247AD9",
    "height": 4.775062070419179,
    "width": 1.445917534621479,
    "x": 14.86170818107912,
    "y": 2.842170943040401e-14
  },
  "hasClippingMask": false,
  "isClosed": true,
  "isFixedToViewport": false,
  "isFlippedHorizontal": false,
  "isFlippedVertical": false,
  "isLocked": false,
  "isVisible": true,
  "layerListExpandedType": 1,
  "name": "Fill 21",
  "nameIsFixed": false,
  "pointRadiusBehaviour": 1,
  "points": [
    {
      "_class": "curvePoint",
      "cornerRadius": 0,
      "curveFrom": "{0, 0.99999999999999933}",
      "curveMode": 1,
      "curveTo": "{0, 0.99999999999999933}",
      "hasCurveFrom": false,
      "hasCurveTo": false,
      "point": "{0, 0.99999999999999933}"
    },
    {
      "_class": "curvePoint",
      "cornerRadius": 0,
      "curveFrom": "{0.99999999999999933, 0.99999999999999933}",
      "curveMode": 1,
      "curveTo": "{0.99999999999999933, 0.99999999999999933}",
      "hasCurveFrom": false,
      "hasCurveTo": false,
      "point": "{0.99999999999999933, 0.99999999999999933}"
    },
    {
      "_class": "curvePoint",
      "cornerRadius": 0,
      "curveFrom": "{0.99999999999999933, 0}",
      "curveMode": 1,
      "curveTo": "{0.99999999999999933, 0}",
      "hasCurveFrom": false,
      "hasCurveTo": false,
      "point": "{0.99999999999999933, 0}"
    },
    {
      "_class": "curvePoint",
      "cornerRadius": 0,
      "curveFrom": "{0, 0}",
      "curveMode": 1,
      "curveTo": "{0, 0}",
      "hasCurveFrom": false,
      "hasCurveTo": false,
      "point": "{0, 0}"
    }
  ],
  "resizingConstraint": 63,
  "resizingType": 0,
  "rotation": 0,
  "shouldBreakMaskChain": false,
  "style": {
    "_class": "style",
    "blur": {
      "_class": "blur",
      "center": "{0.5, 0.5}",
      "do_objectID": "95D07BC0-AA96-4A8E-A9FC-18BE3FE93B99",
      "isEnabled": false,
      "motionAngle": 0,
      "radius": 3.919999999999999,
      "saturation": 1,
      "type": 0
    },
    "borders": [
      {
        "_class": "border",
        "color": {
          "_class": "color",
          "alpha": 1,
          "blue": 1,
          "green": 1,
          "red": 1
        },
        "fillType": 0,
        "isEnabled": true,
        "position": 0,
        "thickness": 0.9799999999999999
      }
    ],
    "do_objectID": "F8BCF57A-3EDB-471A-8E42-23F2525B9B59",
    "endMarkerType": 0,
    "fills": [
      {
        "_class": "fill",
        "color": {
          "_class": "color",
          "alpha": 1,
          "blue": 1,
          "green": 1,
          "red": 1
        },
        "fillType": 0,
        "isEnabled": true,
        "noiseIndex": 0,
        "noiseIntensity": 0,
        "patternFillType": 1,
        "patternTileScale": 1
      }
    ],
    "miterLimit": 10,
    "startMarkerType": 0,
    "windingRule": 1
  }
}