{
  "_class": "shapePath",
  "booleanOperation": -1,
  "clippingMaskMode": 0,
  "do_objectID": "3D361070-2462-4F55-AAB0-AB51990948A2",
  "edited": true,
  "exportOptions": {
    "_class": "exportOptions",
    "do_objectID": "E40E4A1E-99CD-4AE4-8B23-4CEAF037E5F7",
    "exportFormats": [
    ],
    "includedLayerIds": [
    ],
    "layerOptions": 0,
    "shouldTrim": false
  },
  "frame": {
    "_class": "rect",
    "constrainProportions": false,
    "do_objectID": "79396362-6B4C-4BF9-96B4-AEB8C008E4E8",
    "height": 15.2303757503139,
    "width": 28.14486223317742,
    "x": 77.39600809412562,
    "y": 0.9024154368833767
  },
  "hasClippingMask": false,
  "isClosed": false,
  "isFixedToViewport": false,
  "isFlippedHorizontal": false,
  "isFlippedVertical": false,
  "isLocked": false,
  "isVisible": true,
  "layerListExpandedType": 1,
  "name": "Fill 13",
  "nameIsFixed": false,
  "pointRadiusBehaviour": 1,
  "points": [
    {
      "_class": "curvePoint",
      "cornerRadius": 0,
      "curveFrom": "{0.74669004409466699, 0}",
      "curveMode": 4,
      "curveTo": "{0.75177600511099396, 0}",
      "hasCurveFrom": true,
      "hasCurveTo": false,
      "point": "{0.75177600511099396, 0}"
    },
    {
      "_class": "curvePoint",
      "cornerRadius": 0,
      "curveFrom": "{0.62399616283258341, 0.011693563076026271}",
      "curveMode": 3,
      "curveTo": "{0.74156465702395036, 0.00025499981785745456}",
      "hasCurveFrom": true,
      "hasCurveTo": true,
      "point": "{0.73641955692603855, 0.00076499945357132832}"
    },
    {
      "_class": "curvePoint",
      "cornerRadius": 0,
      "curveFrom": "{0.47496567723789296, 0.52041819970128478}",
      "curveMode": 3,
      "curveTo": "{0.5332768116808948, 0.13751775891588636}",
      "hasCurveFrom": true,
      "hasCurveTo": true,
      "point": "{0.50528431306390298, 0.32133619904557126}"
    },
    {
      "_class": "curvePoint",
      "cornerRadius": 0,
      "curveFrom": "{0.5508214058845029, 0.72234162689883652}",
      "curveMode": 3,
      "curveTo": "{0.53751511252783379, 0.68751593748861406}",
      "hasCurveFrom": true,
      "hasCurveTo": true,
      "point": "{0.54019608422636256, 0.69454664675239353}"
    },
    {
      "_class": "curvePoint",
      "cornerRadius": 0,
      "curveFrom": "{0.60168101604776991, 0.68981093584933006}",
      "curveMode": 2,
      "curveTo": "{0.57159893654810123, 0.72897162216312517}",
      "hasCurveFrom": true,
      "hasCurveTo": true,
      "point": "{0.58663997629793529, 0.70940949327893132}"
    },
    {
      "_class": "curvePoint",
      "cornerRadius": 0,
      "curveFrom": "{0.59428863084962058, 0.6225274124804181}",
      "curveMode": 4,
      "curveTo": "{0.60526878699727205, 0.6513788204436981}",
      "hasCurveFrom": true,
      "hasCurveTo": true,
      "point": "{0.59466317836632687, 0.62354741175184691}"
    },
    {
      "_class": "curvePoint",
      "cornerRadius": 0,
      "curveFrom": "{0.59389437030571912, 0.19409128993479252}",
      "curveMode": 3,
      "curveTo": "{0.54788416483243818, 0.49630250264106818}",
      "hasCurveFrom": true,
      "hasCurveTo": true,
      "point": "{0.56945021658383899, 0.3546683180940573}"
    },
    {
      "_class": "curvePoint",
      "cornerRadius": 0,
      "curveFrom": "{0.83926241980269167, 0.11409420421842546}",
      "curveMode": 3,
      "curveTo": "{0.67655109333462637, 0.12990419292557628}",
      "hasCurveFrom": true,
      "hasCurveTo": true,
      "point": "{0.73990876273956485, 0.12374776875159313}"
    },
    {
      "_class": "curvePoint",
      "cornerRadius": 0,
      "curveFrom": "{0.944707402269094, 0.43448326108338359}",
      "curveMode": 3,
      "curveTo": "{0.89790867570801014, 0.21751484463225343}",
      "hasCurveFrom": true,
      "hasCurveTo": true,
      "point": "{0.91947472745941083, 0.31751120177771258}"
    },
    {
      "_class": "curvePoint",
      "cornerRadius": 0,
      "curveFrom": "{0.85018343686875764, 0.81217441987541306}",
      "curveMode": 2,
      "curveTo": "{0.93441720207326973, 0.58252886962223405}",
      "hasCurveFrom": true,
      "hasCurveTo": true,
      "point": "{0.89327611431716958, 0.69469236093402598}"
    },
    {
      "_class": "curvePoint",
      "cornerRadius": 0,
      "curveFrom": "{0.69517990403396246, 0.87683508797493481}",
      "curveMode": 4,
      "curveTo": "{0.77982764280957129, 0.87683508797493481}",
      "hasCurveFrom": false,
      "hasCurveTo": true,
      "point": "{0.69517990403396246, 0.87683508797493481}"
    },
    {
      "_class": "curvePoint",
      "cornerRadius": 0,
      "curveFrom": "{0.014922761586664208, 0.87683508797493481}",
      "curveMode": 4,
      "curveTo": "{0.033334728986854752, 0.87683508797493481}",
      "hasCurveFrom": true,
      "hasCurveTo": false,
      "point": "{0.033334728986854752, 0.87683508797493481}"
    },
    {
      "_class": "curvePoint",
      "cornerRadius": 0,
      "curveFrom": "{0, 0.97242359112600363}",
      "curveMode": 2,
      "curveTo": "{0, 0.90441149684892852}",
      "hasCurveFrom": true,
      "hasCurveTo": true,
      "point": "{0, 0.93843575826017023}"
    },
    {
      "_class": "curvePoint",
      "cornerRadius": 0,
      "curveFrom": "{0.033334728986854752, 0.99999999999999734}",
      "curveMode": 4,
      "curveTo": "{0.014922761586664208, 0.99999999999999734}",
      "hasCurveFrom": false,
      "hasCurveTo": true,
      "point": "{0.033334728986854752, 0.99999999999999734}"
    },
    {
      "_class": "curvePoint",
      "cornerRadius": 0,
      "curveFrom": "{0.80261590224706647, 0.99999999999999734}",
      "curveMode": 4,
      "curveTo": "{0.69517990403396246, 0.99999999999999734}",
      "hasCurveFrom": true,
      "hasCurveTo": false,
      "point": "{0.69517990403396246, 0.99999999999999734}"
    },
    {
      "_class": "curvePoint",
      "cornerRadius": 0,
      "curveFrom": "{1.002446858923439, 0.61658955957888406}",
      "curveMode": 2,
      "curveTo": "{0.89256644533814722, 0.91610505992495483}",
      "hasCurveFrom": true,
      "hasCurveTo": true,
      "point": "{0.94843316440896108, 0.76379731157334652}"
    },
    {
      "_class": "curvePoint",
      "cornerRadius": 0,
      "curveFrom": "{0.94527908005775074, 0.10454992532148183}",
      "curveMode": 3,
      "curveTo": "{1.0150631963282803, 0.42807183709154406}",
      "hasCurveFrom": true,
      "hasCurveTo": true,
      "point": "{0.98137363285191437, 0.27190266292666865}"
    },
    {
      "_class": "curvePoint",
      "cornerRadius": 0,
      "curveFrom": "{0.75177600511099396, 0}",
      "curveMode": 4,
      "curveTo": "{0.8561761971360573, 3.6428545408355704e-05}",
      "hasCurveFrom": false,
      "hasCurveTo": true,
      "point": "{0.75177600511099396, 0}"
    }
  ],
  "resizingConstraint": 63,
  "resizingType": 0,
  "rotation": 0,
  "shouldBreakMaskChain": false,
  "style": {
    "_class": "style",
    "blur": {
      "_class": "blur",
      "center": "{0.5, 0.5}",
      "do_objectID": "27B5CEDC-ED61-40F6-9FCF-DE6F7472B3E5",
      "isEnabled": false,
      "motionAngle": 0,
      "radius": 5.6,
      "saturation": 1,
      "type": 0
    },
    "borders": [
      {
        "_class": "border",
        "color": {
          "_class": "color",
          "alpha": 1,
          "blue": 1,
          "green": 1,
          "red": 1
        },
        "fillType": 0,
        "isEnabled": true,
        "position": 0,
        "thickness": 1.4
      }
    ],
    "do_objectID": "E570FF02-E4E4-47C0-9EE4-54C6E8C20774",
    "endMarkerType": 0,
    "fills": [
      {
        "_class": "fill",
        "color": {
          "_class": "color",
          "alpha": 1,
          "blue": 1,
          "green": 1,
          "red": 1
        },
        "fillType": 0,
        "isEnabled": true,
        "noiseIndex": 0,
        "noiseIntensity": 0,
        "patternFillType": 1,
        "patternTileScale": 1
      }
    ],
    "miterLimit": 10,
    "startMarkerType": 0,
    "windingRule": 1
  }
}