{
  "_class": "shapePath",
  "booleanOperation": -1,
  "clippingMaskMode": 0,
  "do_objectID": "276950B2-2080-4E55-A1F9-3FD75FBD0420",
  "edited": true,
  "exportOptions": {
    "_class": "exportOptions",
    "do_objectID": "C071A17B-CDB7-417F-B182-F76B49935FED",
    "exportFormats": [
    ],
    "includedLayerIds": [
    ],
    "layerOptions": 0,
    "shouldTrim": false
  },
  "frame": {
    "_class": "rect",
    "constrainProportions": false,
    "do_objectID": "17E2A6F8-59B9-4A25-96F1-CD7DB86E051C",
    "height": 23.05167941692599,
    "width": 23.08385900213329,
    "x": 0,
    "y": 0
  },
  "hasClippingMask": false,
  "isClosed": false,
  "isFixedToViewport": false,
  "isFlippedHorizontal": false,
  "isFlippedVertical": false,
  "isLocked": false,
  "isVisible": true,
  "layerListExpandedType": 0,
  "name": "Path",
  "nameIsFixed": false,
  "pointRadiusBehaviour": 1,
  "points": [
    {
      "_class": "curvePoint",
      "cornerRadius": 0,
      "curveFrom": "{0.77808489160217265, 0}",
      "curveMode": 4,
      "curveTo": "{0.49930298514637322, 0}",
      "hasCurveFrom": true,
      "hasCurveTo": false,
      "point": "{0.49930298514637322, 0}"
    },
    {
      "_class": "curvePoint",
      "cornerRadius": 0,
      "curveFrom": "{1, 0.78054298642533937}",
      "curveMode": 2,
      "curveTo": "{1, 0.22359680369692883}",
      "hasCurveFrom": true,
      "hasCurveTo": true,
      "point": "{1, 0.5013719071916819}"
    },
    {
      "_class": "curvePoint",
      "cornerRadius": 0,
      "curveFrom": "{0.22191510839782735, 1}",
      "curveMode": 2,
      "curveTo": "{0.77808489160217265, 1}",
      "hasCurveFrom": true,
      "hasCurveTo": true,
      "point": "{0.49930298514637322, 1}"
    },
    {
      "_class": "curvePoint",
      "cornerRadius": 0,
      "curveFrom": "{0, 0.22359680369692883}",
      "curveMode": 2,
      "curveTo": "{0, 0.78054298642533937}",
      "hasCurveFrom": true,
      "hasCurveTo": true,
      "point": "{0, 0.5013719071916819}"
    },
    {
      "_class": "curvePoint",
      "cornerRadius": 0,
      "curveFrom": "{0.49930298514637322, 0}",
      "curveMode": 4,
      "curveTo": "{0.22191510839782735, 0}",
      "hasCurveFrom": false,
      "hasCurveTo": true,
      "point": "{0.49930298514637322, 0}"
    }
  ],
  "resizingConstraint": 63,
  "resizingType": 0,
  "rotation": 0,
  "shouldBreakMaskChain": false,
  "style": {
    "_class": "style",
    "blur": {
      "_class": "blur",
      "center": "{0.5, 0.5}",
      "do_objectID": "4DEE2878-F56A-45C2-8999-B2DB99BEA6EE",
      "isEnabled": false,
      "motionAngle": 0,
      "radius": 5.6,
      "saturation": 1,
      "type": 0
    },
    "borders": [
      {
        "_class": "border",
        "color": {
          "_class": "color",
          "alpha": 1,
          "blue": 1,
          "green": 1,
          "red": 1
        },
        "fillType": 0,
        "isEnabled": true,
        "position": 0,
        "thickness": 1.4
      }
    ],
    "do_objectID": "19ABA9F8-5FBE-4E77-82D4-D4837B35EF0B",
    "endMarkerType": 0,
    "fills": [
      {
        "_class": "fill",
        "color": {
          "_class": "color",
          "alpha": 1,
          "blue": 1,
          "green": 1,
          "red": 1
        },
        "fillType": 0,
        "isEnabled": true,
        "noiseIndex": 0,
        "noiseIntensity": 0,
        "patternFillType": 1,
        "patternTileScale": 1
      }
    ],
    "miterLimit": 10,
    "startMarkerType": 0,
    "windingRule": 1
  }
}